<tokens>
	<token value="10">ZEUS_STARTING_FAVOR_BONUS</token>
	<token value="20">ZEUS_FAVOR_SPEED</token>
	<token value="1">ZEUS_MYTH_UNIT_COST</token>
	<token value="60">ZEUS_INFANTRY_BUILDING_DAMAGE_BONUS</token>
	<token value="15">ZEUS_HOPLITES_MOVEMENT_BONUS</token>
	<token value="20">HADES_FALLEN_SHADE_RETURN_CHANCE</token>
	<token value="15">HADES_MYTH_UNIT_HP_BONUS</token>
	<token value="1">HADES_RANGED_BONUS</token>
	<token value="1">HADES_LOS_BONUS</token>
	<token value="2">HADES_RANGED_FORITIFATION_RANGE_BONUS</token>
	<token value="0.1">POSEIDON_UNITS_SPEED_BONUS</token>
	<token value="30">POSEIDON_STABLE_MARKET_CHEAP</token>
	<token value="15">POSEIDON_MARKET_RATE_IMPROVEMENT</token>
	<token value="1">DEMETER_FARMER_COUNT_IMPROVEMENT</token>
	<token value="2">DEMETER_TC_PROJECTILE_NUM_IMPROVEMENT</token>
	<token value="5">DEMETER_TC_PROJECTILE_RANGE_IMPROVEMENT</token>
	<token value="25">RA_GATHER_BONUS</token>
	<token value="15">RA_HP_BONUS</token>
	<token value="60">RA_PHARAOH_EFFICIENCY</token>
	<token value="5">ISIS_TOWN_CENTER_POPULATION_BONUS</token>
	<token value="25">ISIS_MONUMENT_SHIELD_RANGE</token>
	<token value="50">ISIS_MONUMENT_SHIELD_RANGE_EMPOWERED</token>
	<token value="50">ISIS_MONUMENT_HEAL_RANGE</token>
	<token value="100">ISIS_FAVOR_GEN_SPEED</token>
	<token value="10">ISIS_TECH_COST_REDUCTION</token>
	<token value="5">ISIS_OBELISK_COST</token>
	<token value="60">ISIS_OBELISK_BUILD_SPEED</token>
	<token value="25">SET_CONVERT_FOOD_LOSS</token>
	<token value="5">SET_UNIT_SPEED_BONUS</token>
	<token value="25">SET_BUILDING_COST</token>
	<token value="10">SET_BUILDING_UNIT_COST_REDUCTION</token>
	<token value="10">THOR_DWARVE_COST_REDUCTION</token>
	<token value="3">THOR_EXTRA_DWARVEN_ARMORY_UPGRADES</token>
	<token value="10">THOR_ARMORY_COST_REDUCTION</token>
	<token value="10">ODIN_GATHERER_DWARVEN_HUNT_BONUS</token>
	<token value="25">ODIN_GREAT_HALL_FAVOR_GENERATE</token>
	<token value="0.4">ODIN_HUMAN_HERO_HP_REGEN</token>
	<token value="2">ODIN_RAVEN_SCOUT_SPAWNS</token>
	<token value="15">LOKI_HUMAN_CONTRIBUTION</token>
	<token value="50">LOKI_HERSIRS_CONTRIBUTION</token>
	<token value="10">LOKI_HUMAN_HERO_COUNTER_DAMAGE</token>
	<token value="10">LOKI_BUILDING_SPEED_BONUS</token>
	<token value="50">LOKI_OXCART_COST_REDUCTION</token>
	<token value="50">LOKI_BERSERK_TRANSFORM_COST_REDUCTION</token>
	<token value="50">FREYR_TECHNOLOGY_COST</token>
	<token value="150">FREYR_TECHNOLOGY_RESEARCH_DURATION</token>
	<token value="10">FREYR_HILL_FORTS_UNITS_DAMAGE_BONUS</token>
	<token value="50">KRONOS_TOWER_PALACE_SHIFT_COST</token>
	<token value="25">KRONOS_MANOR_CONSTRUCTION_SPEED_BONUS</token>
	<token value="2">KRONOS_FREE_MYTH_UNIT_COUNT</token>
	<token value="20">KRONOS_LOST_SIEGE_MYTH_UNITS_COST_RETURN</token>
	<token value="4">ORANOS_UNIT_LOS_BONUS</token>
	<token value="25">ORANOS_ORACLE_LOS_FAVOR_BONUS</token>
	<token value="25">ORANOS_DAMAGED_UNITS_VISIBLE_DURATION</token>
	<token value="25">GAIA_CITIZEN_HERO_PROMOTION_COST_REDUCTION</token>
	<token value="35">GAIA_GUILD_TECHNOLOGIES_COST_REDUCTION</token>
	<token value="1">GAIA_LUSH_FRIENDLY_HEALING</token>
	<token value="4">FUXI_YIN_YANG_DURATION</token>
	<token value="10">FUXI_YIN_ECONOMIC_GATHER_RATE</token>
	<token value="10">FUXI_YANG_HUMAN_SOLDIERS_SIEGE_DAMAGE</token>
	<token value="300">FUXI_FAVORED_LAND_RESEARCH_SPEED</token>
	<token value="25">FUXI_ADDONS_COST_REDUCTION</token>
	<token value="25">NUWA_PEASANT_AGE_COST_REDUCTION</token>
	<token value="1">NUWA_FAVORED_LAND_SPREAD_INCREASE</token>
	<token value="1.5">SHENNONG_MYTH_UNIT_REGEN</token>
	<token value="300">AMATERASU_PASSIVE_XP_BONUS</token>
	<token value="140">AMATERASU_RESOURCE_INVENTORY_CAP</token>
	<token value="2">AMATERASU_COMBAT_REGEN_MULTIPLIER</token>
	<token value="25">TSUKUYOMI_FASTER_AGE_ADVANCEMENT</token>
	<token value="25">SUSANOO_GOD_POWER_COST_REDUCTION</token>
	<token value="25">SUSANOO_UNIT_RECHARGE_TIME</token>
	<token value="250">DEMETER_MYTH_BATTLE_FAVOR_OBJECTIVE</token>
	<token value="50">DEMETER_MIDAS_TOUCH_REWARD_AMOUNT</token>
</tokens>